CHANGES.txt
COPYING.txt
MANIFEST.in
README.txt
RELEASE.txt
demo.py
pyproject.toml
setup.py
detectors/README.txt
detectors/creator_resolution.py
detectors/emailauditor.py
detectors/irker.py
detectors/newissuecopy.py
detectors/newitemcopy.py
doc/CVE.txt
doc/FAQ.txt
doc/Makefile
doc/acknowledgements.txt
doc/admin_guide.txt
doc/admin_help.html
doc/announcement.txt
doc/conf.py
doc/customizing.txt
doc/default.css
doc/design.txt
doc/developers.txt
doc/features.txt
doc/format_config.awk
doc/glossary.txt
doc/implementation.txt
doc/index.txt
doc/installation.txt
doc/license.txt
doc/man_pages.txt
doc/mysql.txt
doc/overview.txt
doc/postgresql.txt
doc/pydoc.txt
doc/reference.txt
doc/requirements.pip
doc/rest.txt
doc/roundup-favicon.ico
doc/roundup-server.ini.example
doc/sc.txt
doc/security-history.txt
doc/security.txt
doc/tracker_config.txt
doc/tracker_templates.txt
doc/upgrading-history.txt
doc/upgrading.txt
doc/user_guide.txt
doc/whatsnew-0.7.txt
doc/whatsnew-0.8.txt
doc/xmlrpc.txt
doc/_static/style.css
doc/_templates/layout.html
doc/html_extra/original_overview.html
doc/html_extra/roundup_short_paper.html
doc/html_extra/spec.html
doc/html_extra/images/bugzilla-1.gif
doc/html_extra/images/bugzilla-2.gif
doc/html_extra/images/bugzilla-3.gif
doc/html_extra/images/bugzilla-4.gif
doc/html_extra/images/edit.png
doc/html_extra/images/hyperdb.png
doc/html_extra/images/jitterbug-1.gif
doc/html_extra/images/jitterbug-2.gif
doc/html_extra/images/logo-acl-medium.png
doc/html_extra/images/logo-codesourcery-medium.png
doc/html_extra/images/logo-software-carpentry-standard.png
doc/html_extra/images/roundup-1.png
doc/html_extra/images/roundup.png
doc/html_extra/man_pages/roundup-admin.1.html
doc/html_extra/man_pages/roundup-demo.1.html
doc/html_extra/man_pages/roundup-mailgw.1.html
doc/html_extra/man_pages/roundup-server.1.html
doc/images/classhelper-issue-all.png
doc/images/edit_issue.png
doc/images/index_logged_in.png
doc/images/index_logged_out.png
doc/images/my_details.png
roundup.egg-info/PKG-INFO
roundup.egg-info/SOURCES.txt
roundup.egg-info/dependency_links.txt
roundup.egg-info/entry_points.txt
roundup.egg-info/requires.txt
roundup.egg-info/top_level.txt
