Metadata-Version: 2.1
Name: roundup
Version: 2.5.0
Summary: A simple-to-use and -install issue-tracking system with command-line, web and e-mail interfaces. Highly customisable.
Home-page: https://www.roundup-tracker.org
Download-URL: https://pypi.org/project/roundup
Author: Richard Jones
Author-email: richard@users.sourceforge.net
Maintainer: Ralf Schlatterbeck
Maintainer-email: rsc@runtux.com
License: OSI Approved: MIT License, Zope Public License, Python Software Foundation License
Project-URL: Documentation, https://roundup-tracker.org/docs.html
Project-URL: Changelog, https://sourceforge.net/p/roundup/code/ci/tip/tree/CHANGES.txt
Project-URL: Contact, https://roundup-tracker.org/contact.html
Project-URL: IRC, https://webchat.oftc.net/?randomnick=1&channels=roundup&prompt=1
Project-URL: Issues, https://issues.roundup-tracker.org/
Project-URL: Licenses, https://roundup-tracker.org/docs/license.html
Project-URL: Wiki, https://wiki.roundup-tracker.org/
Classifier: Development Status :: 5 - Production/Stable
Classifier: Environment :: Console
Classifier: Environment :: Web Environment
Classifier: Intended Audience :: Customer Service
Classifier: Intended Audience :: Information Technology
Classifier: Intended Audience :: End Users/Desktop
Classifier: Intended Audience :: Developers
Classifier: Intended Audience :: System Administrators
Classifier: License :: OSI Approved
Classifier: License :: OSI Approved :: MIT License
Classifier: License :: OSI Approved :: Zope Public License
Classifier: License :: OSI Approved :: Python Software Foundation License
Classifier: Operating System :: MacOS :: MacOS X
Classifier: Operating System :: Microsoft :: Windows
Classifier: Operating System :: POSIX
Classifier: Programming Language :: Python
Classifier: Programming Language :: Python :: 3
Classifier: Programming Language :: Python :: 3.7
Classifier: Programming Language :: Python :: 3.8
Classifier: Programming Language :: Python :: 3.9
Classifier: Programming Language :: Python :: 3.10
Classifier: Programming Language :: Python :: 3.11
Classifier: Programming Language :: Python :: 3.12
Classifier: Programming Language :: Python :: 3.13
Classifier: Programming Language :: Python :: Implementation :: CPython
Classifier: Topic :: Communications :: Email
Classifier: Topic :: Office/Business
Classifier: Topic :: Software Development :: Bug Tracking
Classifier: Topic :: Internet :: WWW/HTTP :: WSGI :: Application
Requires-Python: >=3.7
License-File: COPYING.txt
Provides-Extra: charting
Requires-Dist: pygal; extra == "charting"
Provides-Extra: jinja2
Requires-Dist: jinja2; extra == "jinja2"
Provides-Extra: extras
Requires-Dist: brotli; extra == "extras"
Requires-Dist: pytz; extra == "extras"
Provides-Extra: test
Requires-Dist: pytest>7.0.0; extra == "test"
